TsProject/TsExtra.py
TsProject/TsINIT.txt
TsProject/TsPost.py
TsProject/__init__.py
TsProject/__pycache__/TsPost.cpython-38.pyc
TsProject-1.0.7.dist-info/METADATA
TsProject-1.0.7.dist-info/WHEEL
TsProject-1.0.7.dist-info/entry_points.txt
TsProject-1.0.7.dist-info/top_level.txt
TsProject-1.0.7.dist-info/zip-safe
TsProject-1.0.7.dist-info/RECORD
